q/http/__init__.py
q/http/client/__init__.py
q/http/client/__init__.pyi
q/http/client/queue.py
q/http/client/read.py
q/http/client/request.py
q/http/client/util.py
q/http/client/write.py
q/http/server/__init__.py
q/http/server/__init__.pyi
q/http/server/queue.py
q/http/server/read.py
q/http/server/util.py
q/http/server/write.py
queue_http-0.1.7.dist-info/METADATA
queue_http-0.1.7.dist-info/WHEEL
queue_http-0.1.7.dist-info/top_level.txt
queue_http-0.1.7.dist-info/RECORD
